{
  "name": "Eugenia Allen",
  "age": 33,
  "address": {
    "street": "Pipo Lane",
    "city": "Roebto",
    "state": "WV",
    "zip": "40022"
  },
  "contact": {
    "phone": "(283) 864-9974",
    "servicePhone": "800852196"
  },
  "birthday": "1965-11-11T01:03:55.772Z",
  "ip": "200.5.185.104",
  "foo": "bar",
  "profile": {
    "about": "Suanuned hawocpen ja ozoin fuboj arrefar nesnisni otiget upuzut citag jirruwse adicurvef. Olibo biriweoco ceec sejduhvo vec oggujil edbol bi ne wapowto ivilaba hic ko pi inupeb guwved agmaj. Cerecu ima co emuh cirpav tijakuguh fi pe wurefe edpanuv fob sekhehusi ki ha pasugnuh. Bu idiku oges hev deke ji pekir cecuzuro giv daka dalo vadi. Bi omagah dintehim anib vi nenhauci hakih gobjibo vem ki hav morugbar.",
    "bio": "Niszuhzuw uj zaputin enuza duiw ipbazu vu pa dov kagulel kudel aw ce huwsog me. Zuiv acolozfe susonoj ohhija to fak mazmo fanucu beklo dumhelpal isarim fihogaka cat. Tu huw ipu lo himojebo lo mecasmun vuvuni orik bemiis wi levnuton dafa il bac ebribir."
  },
  "apiKey": "4534f4bd735856731791e068a30e6733fbd50fa1bfd38cd1eda2b9365285a612",
  "currency": {
    "code": "XPF",
    "name": "Comptoirs Français du Pacifique (CFP) Franc"
  }
}