{
  "name": "Virgie Matthews",
  "age": 21,
  "address": {
    "street": "Mabje Place",
    "city": "Vocowo",
    "state": "WA",
    "zip": "76097"
  },
  "contact": {
    "phone": "(471) 843-3234",
    "servicePhone": "800164458"
  },
  "birthday": "1986-11-13T22:01:15.483Z",
  "ip": "156.157.190.173",
  "foo": "bar",
  "profile": {
    "about": "Ne hejaw ug ubilubute beshac kikgaz fom tisa fur dowso naz vojlaiz kekumha fuhiavo ziszu odu oz kom. Pikdowwo cap ji of cuj gikisa za amdin he motbepe hesimdof suz veho. Ihubukaro mi futapefec fet tarujma sakacagod kibujsa favaj ji limdul teneb se uru dowge. Kah zoawot mare pinci fapope makok zo aghib hihmos vum vo nipok wec iku kerpegdir. Poz siztekaga tucepula horumlog fu vujvuat inawu jodal piwgi ne esaofva reoguwe. Viksi zat dizki jace biprat tomotsac aguih paj oce zowiret vecordev buwnihcav.",
    "bio": "Ebajili ni secoz usi gufwenpev av awi unehepa kus bunal asuepene ovi wosaj. Huboron givuwhag iwe oj moszi cudpizaw hortoj vulzu ivi papsot hoib ur. Da ne giwzihre la ga uvtemwet ulfodo ithi zo imeuk urpag cejafeuk ediildiw bo ebje siormik keki. Te lukotemi hojrofzip bupud ha masatapu re wizho gehof iv tubiv awtownim ta rakan."
  },
  "apiKey": "92f62d953c39c77995975d83ea5f1a00e371e1881376d0165537665f72446dc1",
  "currency": {
    "code": "PLN",
    "name": "Poland Zloty"
  }
}